youtubedata/__init__.py
youtubedata/youtubedata.py
youtubedata-1.0.9.dist-info/LICENSE.txt
youtubedata-1.0.9.dist-info/METADATA
youtubedata-1.0.9.dist-info/WHEEL
youtubedata-1.0.9.dist-info/top_level.txt
youtubedata-1.0.9.dist-info/RECORD
